num2words_bd_inr/__init__.py
num2words_bd_inr/num2words_bd_inr.py
num2words_bd_inr-0.1.0.dist-info/licenses/LICENSE
tests/__init__.py
tests/test_num2words_bd_inr.py
num2words_bd_inr-0.1.0.dist-info/METADATA
num2words_bd_inr-0.1.0.dist-info/WHEEL
num2words_bd_inr-0.1.0.dist-info/top_level.txt
num2words_bd_inr-0.1.0.dist-info/RECORD
