Metadata-Version: 2.4
Name: num2words-BD-INR
Version: 0.1.0
Summary: Convert numerical amounts to words with support for Indian and Bangladeshi currency formats/numberinc system
Home-page: https://github.com/RifatAnwarRobin/num2words-BD-INR
Author: Rifat Anwar
Author-email: rifatanwarrobin@gmail.com
Keywords: INR,BD,num2words_bd_inr,amounttowords,num2words,amount,currency,words,conversion,indian,bangladeshi,taka,rupee,format,lakh,koti,crore,hazar,thousand
Classifier: Programming Language :: Python :: 3
Classifier: Programming Language :: Python :: 3.10
Classifier: License :: OSI Approved :: MIT License
Classifier: Operating System :: OS Independent
Requires-Python: >=3.10
License-File: LICENSE
Requires-Dist: num2words
Dynamic: author
Dynamic: author-email
Dynamic: classifier
Dynamic: description
Dynamic: description-content-type
Dynamic: home-page
Dynamic: keywords
Dynamic: license-file
Dynamic: requires-dist
Dynamic: requires-python
Dynamic: summary
